esp_batch_flash/__init__.py
esp_batch_flash/base.py
esp_batch_flash/cli.py
esp_batch_flash/mock.py
esp_batch_flash-0.2.0.dist-info/licenses/LICENSE
esp_batch_flash-0.2.0.dist-info/METADATA
esp_batch_flash-0.2.0.dist-info/WHEEL
esp_batch_flash-0.2.0.dist-info/entry_points.txt
esp_batch_flash-0.2.0.dist-info/top_level.txt
esp_batch_flash-0.2.0.dist-info/RECORD
