Metadata-Version: 2.4
Name: esp-batch-flash
Version: 0.2.0
Summary: A tool for parallel flashing multiple ESP32 devices
Home-page: https://github.com/leeebo/esp-batch-flash
Author: leeebo
Author-email: liboogo@gmail.com
Project-URL: Bug Tracker, https://github.com/leeebo/esp-batch-flash/issues
Classifier: Programming Language :: Python :: 3
Classifier: License :: OSI Approved :: Apache Software License
Classifier: Operating System :: OS Independent
Classifier: Development Status :: 4 - Beta
Classifier: Intended Audience :: Developers
Classifier: Topic :: Software Development :: Embedded Systems
Requires-Python: >=3.8
License-File: LICENSE
Requires-Dist: esptool>=4.0
Requires-Dist: pyserial>=3.4
Dynamic: author
Dynamic: author-email
Dynamic: classifier
Dynamic: description
Dynamic: description-content-type
Dynamic: home-page
Dynamic: license-file
Dynamic: project-url
Dynamic: requires-dist
Dynamic: requires-python
Dynamic: summary
